Metadata-Version: 1.0
Name: llu-distributions
Version: 1.0
Summary: Gaussian and Binomial distributions
Home-page: UNKNOWN
Author: Leqi Lu
Author-email: leqilu67@gmail.com
License: UNKNOWN
Platform: UNKNOWN
